polymage/__init__.py
polymage/registry.py
polymage/agent/__init__.py
polymage/agent/agent.py
polymage/agent/image_captioner_agent.py
polymage/agent/image_generator_agent.py
polymage/agent/instruct_agent.py
polymage/data/models/flux.yaml
polymage/data/models/gemma-3.yaml
polymage/data/models/gpt-oss.yaml
polymage/data/models/hidream.yaml
polymage/data/models/others.yaml
polymage/data/models/qwen-image.yaml
polymage/data/models/qwen3.yaml
polymage/data/models/z-image.yaml
polymage/media/__init__.py
polymage/media/image_media.py
polymage/media/media.py
polymage/model/__init__.py
polymage/model/model.py
polymage/platform/__init__.py
polymage/platform/cloudflare.py
polymage/platform/drawthings.py
polymage/platform/groq.py
polymage/platform/huggingface.py
polymage/platform/lmstudio.py
polymage/platform/platform.py
polymage/platform/togetherai.py
polymage/utils/image_utils.py
polymage/utils/json_utils.py
polymage-0.0.3.dist-info/licenses/LICENSE
polymage-0.0.3.dist-info/METADATA
polymage-0.0.3.dist-info/WHEEL
polymage-0.0.3.dist-info/top_level.txt
polymage-0.0.3.dist-info/RECORD
