Metadata-Version: 2.4
Name: polymage
Version: 0.0.3
Summary: polymage : a multimodal agent python library
Author-email: Fabrice Gaillard <fgaillard@w3architect.com>, Philippe Gaillard <philippe@gaillard.xyz>
License: Apache 2.0
Requires-Python: >=3.13
License-File: LICENSE
Requires-Dist: groq>=0.37.1
Requires-Dist: huggingface-hub>=1.2.3
Requires-Dist: openai>=2.11.0
Requires-Dist: pillow>=12.0.0
Requires-Dist: pydantic>=2.12.5
Requires-Dist: requests>=2.32.5
Requires-Dist: tenacity>=9.1.2
Dynamic: license-file
